speaking_eye
