Metadata-Version: 2.1
Name: speaking-eye
Version: 0.1.1
Summary: Track & analyze your computer activity. Focus on work and don't forget to take breaks
Home-page: https://github.com/alena-bartosh/speaking-eye
Author: Alena Bartosh
Author-email: alena.mathematics@gmail.com
License: UNKNOWN
Keywords: worktracker timetracker gtk wnck dash
Platform: UNKNOWN
Classifier: Development Status :: 5 - Production/Stable
Classifier: License :: OSI Approved :: MIT License
Classifier: Operating System :: POSIX :: Linux
Classifier: Programming Language :: Python :: 3
Requires-Python: >=3.6, <4
